clorm/__init__.py
clorm/_clingo.py
clorm/clingo.py
clorm/json.py
clorm/monkey.py
clorm/py.typed
clorm/lib/__init__.py
clorm/lib/boolean.py
clorm/lib/date.py
clorm/lib/timeslot.py
clorm/orm/__init__.py
clorm/orm/_queryimpl.py
clorm/orm/_typing.py
clorm/orm/atsyntax.py
clorm/orm/core.py
clorm/orm/factbase.py
clorm/orm/factcontainers.py
clorm/orm/lark_fact_parser.py
clorm/orm/noclingo.py
clorm/orm/query.py
clorm/orm/symbols_facts.py
clorm/orm/templating.py
clorm/orm/types.py
clorm/util/__init__.py
clorm/util/oset.py
clorm/util/tools.py
clorm/util/wrapper.py
Clorm-1.5.1.dist-info/LICENSE
Clorm-1.5.1.dist-info/METADATA
Clorm-1.5.1.dist-info/WHEEL
Clorm-1.5.1.dist-info/top_level.txt
Clorm-1.5.1.dist-info/RECORD
