Metadata-Version: 2.1
Name: Clorm
Version: 1.5.1
Summary: Clingo ORM (CLORM) provides a ORM interface for interacting with the Clingo Answer Set Programming (ASP) solver
Home-page: https://github.com/potassco/clorm
Author: David Rajaratnam
Author-email: daver@gemarex.com.au
License: MIT
License-File: LICENSE
Requires-Dist: clingo
